envclass/__init__.py
envclass/envclass.py
envclass/metaclass.py
envclass-1.1.0.dist-info/LICENSE
envclass-1.1.0.dist-info/METADATA
envclass-1.1.0.dist-info/WHEEL
envclass-1.1.0.dist-info/top_level.txt
envclass-1.1.0.dist-info/RECORD
